showmethef1ag/__init__.py
showmethef1ag/test.py
showmethef1ag-0.1.0.dist-info/METADATA
showmethef1ag-0.1.0.dist-info/WHEEL
showmethef1ag-0.1.0.dist-info/entry_points.txt
showmethef1ag-0.1.0.dist-info/top_level.txt
showmethef1ag-0.1.0.dist-info/RECORD
